powerlinecust/__init__.py
powerlinecust/segments/__init__.py
powerlinecust/segments/common.py
powerlinecust/segments/mem_usage.py
powerlinecust_segments-0.1.0.dist-info/LICENSE
powerlinecust_segments-0.1.0.dist-info/METADATA
powerlinecust_segments-0.1.0.dist-info/WHEEL
powerlinecust_segments-0.1.0.dist-info/top_level.txt
powerlinecust_segments-0.1.0.dist-info/RECORD
