Metadata-Version: 2.1
Name: powerlinecust-segments
Version: 0.1.0
Summary: Powerline Custom Segments
Author: Avijit Pal
License: MIT License
Project-URL: Homepage, https://github.com/avijitpal9/powerlinecust-segments
Keywords: powerline,memory,pyenv,jenv,docker
Classifier: License :: OSI Approved :: MIT License
Classifier: Programming Language :: Python
Classifier: Programming Language :: Python :: 3
Requires-Python: >=3.9
License-File: LICENSE
Requires-Dist: psutil
Requires-Dist: powerline-status >=2.7
Provides-Extra: dev
Requires-Dist: twine ; extra == 'dev'
Requires-Dist: build ; extra == 'dev'
Requires-Dist: pip-tools ; extra == 'dev'
